Workbook

Sheet Travel Log
A1: Date | B1: CEO | C1: Co. | D1: Destination | E1: Hub | F1: Counterparty / Event | G1: Stated Purpose | H1: Linked Entity (Ticker) | I1: Framework Tie | J1: Trip Type | K1: Signal | L1: Conf. | M1: Source | N1: Notes
A2: 2026-05-23 | B2: Huang | C2: NVDA | D2: Taipei, Taiwan | E2: Taiwan | F2: TSMC (C.C. Wei), Foxconn (Young Liu), MediaTek, Delta; Computex + GTC Week | G2: Supply-chain mgmt; Vera Rubin partners; Taipei HQ groundbreak May 27 | H2: TSM, Foxconn(2317), MediaTek, Delta | I2: Vertical Integration Bifurcation / Second Order | J2: Scheduled set-piece | K2: Coincident | L2: Conf. | M2: Taiwan News / Focus Taiwan, 5/23/26 | N2: Recurring (Jan + June yearly). HQ groundbreak = physical commitment, watch.
A3: 2026-01-24 | B3: Huang | C3: NVDA | D3: Shanghai→Beijing→Shenzhen→Taiwan | E3: China-Mainland | F3: Nvidia China staff (Lunar NY); regulators | G3: Routine annual visit; China $50B opportunity amid local competition | H3: China market | I3: China access / export-control | J3: Routine-recurring | K3: Coincident | L3: Conf. | M3: Reuters/AOL, 1/24/26 | N3: Routed China→Taiwan in one trip; standard cadence.
A4: ~2026-05-13 | B4: Huang | C4: NVDA | D4: Beijing, China | E4: China-Mainland | F4: Trump delegation; Xi summit | G4: Last-minute add; chip-export leeway in China | H4: China market | I4: China realignment / Hollow Bottom (political) | J4: Delegation-political | K4: Coincident | L4: Conf. | M4: Bloomberg, 5/13/26 | N4: Added Tues before; 3 Mag-7 CEOs on one 36-hr trip.
A5: ~2026-05-13 | B5: Cook | C5: AAPL | D5: Beijing, China | E5: China-Mainland | F5: Trump delegation; Xi summit | G5: Tariffs / China market / supply chain | H5: Foxconn(2317), Pegatron(4938) | I5: China dependence | J5: Delegation-political | K5: Coincident | L5: Conf. | M5: Bloomberg, 5/13/26 | N5: Same delegation as Huang + Musk.
A6: ~2026-05-13 | B6: Musk | C6: TSLA | D6: Beijing, China | E6: China-Mainland | F6: Trump delegation; Xi summit | G6: Tariffs; Shanghai gigafactory; FSD approval | H6: Shanghai Gigafactory | I6: China realignment | J6: Delegation-political | K6: Coincident | L6: Conf. | M6: Bloomberg, 5/13/26 | N6: Same delegation.
A7: 2026-03-18→23 | B7: Cook | C7: AAPL | D7: Chengdu→Beijing, China | E7: China-Mainland | F7: China Development Forum 2026; Vice-Premier He Lifeng | G7: Charm offensive amid antitrust pressure; App Store concessions | H7: Foxconn(2317), Pegatron(4938) | I7: China dependence / supply shift | J7: Scheduled set-piece | K7: Coincident | L7: Conf. | M7: Global Times/Fortune, 3/22/26 | N7: CDF is ANNUAL (every March) = noise. India trip would be the tell.
A8: ~2025-05 | B8: Huang | C8: NVDA | D8: Riyadh, Saudi Arabia | E8: Gulf-Saudi | F8: Trump Saudi visit; MBS / PIF | G8: Court sovereign AI capital | H8: HUMAIN / PIF | I8: Energy Ceiling / sovereign-AI capital | J8: Delegation-political | K8: Coincident | L8: Conf. | M8: AOL/Independent, 5/25 | N8: Cluster of 5+ US tech CEOs on one trip.
A9: ~2025-05 | B9: Musk | C9: TSLA | D9: Riyadh, Saudi Arabia | E9: Gulf-Saudi | F9: Trump Saudi visit; MBS | G9: Sovereign AI capital (xAI too) | H9: HUMAIN / PIF | I9: Energy Ceiling / sovereign-AI capital | J9: Delegation-political | K9: Coincident | L9: Conf. | M9: AOL/Independent, 5/25 | N9: Brother Kimbal + Gracias also along.
A10: ~2025-05 | B10: Jassy | C10: AMZN | D10: Riyadh, Saudi Arabia | E10: Gulf-Saudi | F10: Trump Saudi visit; Saudi officials | G10: Sovereign AI capital | H10: HUMAIN / PIF | I10: Energy Ceiling / sovereign-AI capital | J10: Delegation-political | K10: Coincident | L10: Conf. | M10: AOL/Independent, 5/25 | N10: Amazon at the table.
A11: ~2025-05 | B11: Porat (GOOGL) | C11: GOOGL | D11: Riyadh, Saudi Arabia | E11: Gulf-Saudi | F11: Trump Saudi visit; Saudi officials | G11: Sovereign AI capital (Pres./CIO, not Pichai) | H11: HUMAIN / PIF | I11: Energy Ceiling / sovereign-AI capital | J11: Delegation-political | K11: Coincident | L11: Conf. | M11: AOL/Independent, 5/25 | N11: Google repped by Porat, not Pichai personally.
A12: 2025-11-19 | B12: Huang | C12: NVDA | D12: Washington, DC | E12: US-DC | F12: US-Saudi Investment Forum (Kennedy Center); Trump+MBS | G12: Sovereign AI; US greenlit AI-chip exports to Gulf after | H12: HUMAIN / PIF | I12: Energy Ceiling / sovereign-AI capital | J12: Scheduled set-piece | K12: Coincident | L12: Conf. | M12: CNBC, 11/20/25 | N12: Chip-export approval followed this forum.
... A18: 2026-03 (announced) | B18: Google (corp) | C18: GOOGL | D18: Saudi Arabia | E18: Gulf-Saudi | F18: PIF + HUMAIN JV | G18: $10B global AI hub JV | H18: HUMAIN / PIF | I18: Energy Ceiling / sovereign-AI capital | J18: Structural (deal) | K18: Coincident | L18: Reported | M18: Reuters (your Mag-7 PDF) | N18: Corporate, not personal travel — context row.

Sheet Hub Tally
A1: DESTINATION CLUSTERING — auto-counts from Travel Log
A2: Counts every logged trip by hub. Clustering = where the bodies keep going. Add log rows and these update on recalc.
A4: Hub | B4: Huang | C4: Cook | D4: Pichai | E4: Nadella | F4: Jassy | G4: Zuckerberg | H4: Musk | I4: All (incl. adj.)
A5: Taiwan | B5: =COUNTIFS('Travel Log'!$E:$E,$A5,'Travel Log'!$B:$B,B$4) -> 1 | C5: =COUNTIFS('Travel Log'!$E:$E,$A5,'Travel Log'!$B:$B,C$4) -> 0 | D5: =COUNTIFS('Travel Log'!$E:$E,$A5,'Travel Log'!$B:$B,D$4) -> 0 | E5: =COUNTIFS('Travel Log'!$E:$E,$A5,'Travel Log'!$B:$B,E$4) -> 0 | F5: =COUNTIFS('Travel Log'!$E:$E,$A5,'Travel Log'!$B:$B,F$4) -> 0 | G5: =COUNTIFS('Travel Log'!$E:$E,$A5,'Travel Log'!$B:$B,G$4) -> 0 | H5: =COUNTIFS('Travel Log'!$E:$E,$A5,'Travel Log'!$B:$B,H$4) -> 0 | I5: =COUNTIF('Travel Log'!$E:$E,$A5) -> 1
A6: China-Mainland | B6: =COUNTIFS('Travel Log'!$E:$E,$A6,'Travel Log'!$B:$B,B$4) -> 2 | C6: =COUNTIFS('Travel Log'!$E:$E,$A6,'Travel Log'!$B:$B,C$4) -> 2 | D6: =COUNTIFS('Travel Log'!$E:$E,$A6,'Travel Log'!$B:$B,D$4) -> 0 | E6: =COUNTIFS('Travel Log'!$E:$E,$A6,'Travel Log'!$B:$B,E$4) -> 0 | F6: =COUNTIFS('Travel Log'!$E:$E,$A6,'Travel Log'!$B:$B,F$4) -> 0 | G6: =COUNTIFS('Travel Log'!$E:$E,$A6,'Travel Log'!$B:$B,G$4) -> 0 | H6: =COUNTIFS('Travel Log'!$E:$E,$A6,'Travel Log'!$B:$B,H$4) -> 1 | I6: =COUNTIF('Travel Log'!$E:$E,$A6) -> 5
A7: Gulf-Saudi | B7: =COUNTIFS('Travel Log'!$E:$E,$A7,'Travel Log'!$B:$B,B$4) -> 1 | C7: =COUNTIFS('Travel Log'!$E:$E,$A7,'Travel Log'!$B:$B,C$4) -> 0 | D7: =COUNTIFS('Travel Log'!$E:$E,$A7,'Travel Log'!$B:$B,D$4) -> 0 | E7: =COUNTIFS('Travel Log'!$E:$E,$A7,'Travel Log'!$B:$B,E$4) -> 1 | F7: =COUNTIFS('Travel Log'!$E:$E,$A7,'Travel Log'!$B:$B,F$4) -> 1 | G7: =COUNTIFS('Travel Log'!$E:$E,$A7,'Travel Log'!$B:$B,G$4) -> 0 | H7: =COUNTIFS('Travel Log'!$E:$E,$A7,'Travel Log'!$B:$B,H$4) -> 1 | I7: =COUNTIF('Travel Log'!$E:$E,$A7) -> 6
A8: Gulf-UAE | B8: =COUNTIFS('Travel Log'!$E:$E,$A8,'Travel Log'!$B:$B,B$4) -> 1 | C8: =COUNTIFS('Travel Log'!$E:$E,$A8,'Travel Log'!$B:$B,C$4) -> 0 | D8: =COUNTIFS('Travel Log'!$E:$E,$A8,'Travel Log'!$B:$B,D$4) -> 0 | E8: =COUNTIFS('Travel Log'!$E:$E,$A8,'Travel Log'!$B:$B,E$4) -> 1 | F8: =COUNTIFS('Travel Log'!$E:$E,$A8,'Travel Log'!$B:$B,F$4) -> 0 | G8: =COUNTIFS('Travel Log'!$E:$E,$A8,'Travel Log'!$B:$B,G$4) -> 0 | H8: =COUNTIFS('Travel Log'!$E:$E,$A8,'Travel Log'!$B:$B,H$4) -> 0 | I8: =COUNTIF('Travel Log'!$E:$E,$A8) -> 3
A9: US-DC | B9: =COUNTIFS('Travel Log'!$E:$E,$A9,'Travel Log'!$B:$B,B$4) -> 1 | C9: =COUNTIFS('Travel Log'!$E:$E,$A9,'Travel Log'!$B:$B,C$4) -> 0 | D9: =COUNTIFS('Travel Log'!$E:$E,$A9,'Travel Log'!$B:$B,D$4) -> 0 | E9: =COUNTIFS('Travel Log'!$E:$E,$A9,'Travel Log'!$B:$B,E$4) -> 0 | F9: =COUNTIFS('Travel Log'!$E:$E,$A9,'Travel Log'!$B:$B,F$4) -> 0 | G9: =COUNTIFS('Travel Log'!$E:$E,$A9,'Travel Log'!$B:$B,G$4) -> 0 | H9: =COUNTIFS('Travel Log'!$E:$E,$A9,'Travel Log'!$B:$B,H$4) -> 1 | I9: =COUNTIF('Travel Log'!$E:$E,$A9) -> 2
A10: India | B10: =COUNTIFS('Travel Log'!$E:$E,$A10,'Travel Log'!$B:$B,B$4) -> 0 | C10: =COUNTIFS('Travel Log'!$E:$E,$A10,'Travel Log'!$B:$B,C$4) -> 0 | D10: =COUNTIFS('Travel Log'!$E:$E,$A10,'Travel Log'!$B:$B,D$4) -> 0 | E10: =COUNTIFS('Travel Log'!$E:$E,$A10,'Travel Log'!$B:$B,E$4) -> 0 | F10: =COUNTIFS('Travel Log'!$E:$E,$A10,'Travel Log'!$B:$B,F$4) -> 0 | G10: =COUNTIFS('Travel Log'!$E:$E,$A10,'Travel Log'!$B:$B,G$4) -> 0 | H10: =COUNTIFS('Travel Log'!$E:$E,$A10,'Travel Log'!$B:$B,H$4) -> 0 | I10: =COUNTIF('Travel Log'!$E:$E,$A10) -> 0
A11: Europe | B11: =COUNTIFS('Travel Log'!$E:$E,$A11,'Travel Log'!$B:$B,B$4) -> 0 | C11: =COUNTIFS('Travel Log'!$E:$E,$A11,'Travel Log'!$B:$B,C$4) -> 0 | D11: =COUNTIFS('Travel Log'!$E:$E,$A11,'Travel Log'!$B:$B,D$4) -> 0 | E11: =COUNTIFS('Travel Log'!$E:$E,$A11,'Travel Log'!$B:$B,E$4) -> 0 | F11: =COUNTIFS('Travel Log'!$E:$E,$A11,'Travel Log'!$B:$B,F$4) -> 0 | G11: =COUNTIFS('Travel Log'!$E:$E,$A11,'Travel Log'!$B:$B,G$4) -> 0 | H11: =COUNTIFS('Travel Log'!$E:$E,$A11,'Travel Log'!$B:$B,H$4) -> 0 | I11: =COUNTIF('Travel Log'!$E:$E,$A11) -> 0
A12: Other | B12: =COUNTIFS('Travel Log'!$E:$E,$A12,'Travel Log'!$B:$B,B$4) -> 0 | C12: =COUNTIFS('Travel Log'!$E:$E,$A12,'Travel Log'!$B:$B,C$4) -> 0 | D12: =COUNTIFS('Travel Log'!$E:$E,$A12,'Travel Log'!$B:$B,D$4) -> 0 | E12: =COUNTIFS('Travel Log'!$E:$E,$A12,'Travel Log'!$B:$B,E$4) -> 0 | F12: =COUNTIFS('Travel Log'!$E:$E,$A12,'Travel Log'!$B:$B,F$4) -> 0 | G12: =COUNTIFS('Travel Log'!$E:$E,$A12,'Travel Log'!$B:$B,G$4) -> 0 | H12: =COUNTIFS('Travel Log'!$E:$E,$A12,'Travel Log'!$B:$B,H$4) -> 0 | I12: =COUNTIF('Travel Log'!$E:$E,$A12) -> 0
A13: TOTAL | B13: =SUM(B5:B12) -> 6 | C13: =SUM(C5:C12) -> 2 | D13: =SUM(D5:D12) -> 0 | E13: =SUM(E5:E12) -> 2 | F13: =SUM(F5:F12) -> 1 | G13: =SUM(G5:G12) -> 0 | H13: =SUM(H5:H12) -> 3 | I13: =SUM(I5:I12) -> 17

Sheet Set-Piece Calendar
A1: RECURRING SET-PIECES — the noise filter
A2: A CEO showing up here is EXPECTED. The signal is the ANOMALY: an unscheduled trip, or a destination NOT on this list.
A4: Event | B4: Location | C4: Typical Window | D4: Usual Mag-7 Attendee(s) | E4: Why it's noise
A5: CES | B5: Las Vegas, US | C5: Early January | D5: Huang (keynote) | E5: Annual keynote slot.
A6: WEF / Davos | B6: Davos, Switzerland | C6: Late January | D6: Various | E6: Annual elite gathering.
A7: China 'Two Sessions' | B7: Beijing, China | C7: Early–mid March | D7: — | E7: Sets the CDF backdrop.
A8: China Development Forum | B8: Beijing, China | C8: Late March | D8: Cook (annual) | E8: Cook attends every year.
A9: Nvidia GTC | B9: San Jose, US | C9: March | D9: Huang | E9: Nvidia's own conference.
A10: Apple WWDC | B10: Cupertino, US | C10: June | D10: Cook | E10: Apple dev conference.
A11: Computex | B11: Taipei, Taiwan | C11: Early June | D11: Huang (keynote) | E11: Huang keynotes annually.
A12: Nvidia GTC Week | B12: Taipei, Taiwan | C12: June | D12: Huang | E12: Paired with Computex.
A13: Apple iPhone event | B13: Cupertino, US | C13: September | D13: Cook | E13: Annual product launch.
A14: GITEX / Tech-cation | B14: Dubai, UAE | C14: December (7–11, 2026) | D14: Various | E14: Region's flagship; Gulf draw.
A15: US-Saudi Investment Forum | B15: Washington, DC | C15: (Nov 2025 instance) | D15: Huang, Musk, Jassy | E15: Sovereign-capital set-piece.
A16: Quarterly earnings | B16: HQ / virtual | C16: Jan/Apr/Jul/Oct | D16: All | E16: Scheduled; location ≠ signal.

Sheet Method & Rubric
A1: CEO PHYSICAL-TRAVEL TRACKER — Method & Signal Rubric
A2: Premise: where a CEO spends their scarcest resource (time, in person) leaks strategic intent before deals hit the tape. The Huang/Taiwan tell, applied forward.
A4: THE TWO QUESTIONS THAT TURN A TRIP INTO A SIGNAL
A5: 1) SCHEDULED or ANOMALOUS? A keynote/forum on the Set-Piece Calendar is EXPECTED → noise. An UNSCHEDULED trip, or a trip to a destination NOT on the calendar, is the tell. (e.g. Huang flying to Taipei for a few hours 'only to see TSMC' days before earnings = anomaly. Cook at the March CDF = noise.)
A6: 2) LEADING or COINCIDENT? If the deal is already announced, the trip just confirms it → coincident, low alpha. The alpha is the REPEAT trip to a place with NO announced deal yet. Those are rare and rarely reported — they show up as frequency anomalies before the news.
A7: Highest-value cell = ANOMALOUS + LEADING + repeat visits to a place tied to an implicated company. That is the configuration you wish you'd caught on Huang/Taiwan.
A9: WHAT IS ACTUALLY TRACKABLE (be honest — this is mosaic intel, not a feed)
A10: • Public appearances: conference keynotes, govt summits, ribbon-cuttings, factory openings, earnings-call locations. (Most reliable.)
A11: • Destination-side local press: regional outlets often report a CEO landing before US media does (Focus Taiwan, Gulf News, Global Times).
A12: • Presidential / trade delegations: passenger manifests are published (this is how the Beijing trio and the Riyadh group surfaced).
A13: • Private-jet ADS-B tracking: PARTIAL. Some CEOs block tail numbers via the FAA LADD/PIA programs; coverage is inconsistent. Treat as corroboration, not a primary feed.
A14: • Social / company PR at the destination. Lagging and curated, but confirms presence.
... A29: Seeded May 30, 2026. 2025 rows are baseline cadence; 2026 rows are what to extend. Sources in the log's Source column.
